LICENSE
MANIFEST.in
setup.cfg
setup.py
bitmask/__init__.py
pybitmask.egg-info/PKG-INFO
pybitmask.egg-info/SOURCES.txt
pybitmask.egg-info/dependency_links.txt
pybitmask.egg-info/requires.txt
pybitmask.egg-info/top_level.txt
pybitmask.egg-info/zip-safe