Metadata-Version: 1.1
Name: pybitmask
Version: 1.0.1
Summary: Python 3.4 enumeration inspired bit masks
Home-page: http://bruun.co/
Author: Nick Bruun
Author-email: nick@bruun.co
License: Copyright 2014 Nick Bruun <nick@bruun.co>
